LICENSE
README.md
requirements.txt
setup.py
version.txt
Linum.egg-info/PKG-INFO
Linum.egg-info/SOURCES.txt
Linum.egg-info/dependency_links.txt
Linum.egg-info/entry_points.txt
Linum.egg-info/requires.txt
Linum.egg-info/top_level.txt
linum/__init__.py
linum/cli.py
linum/color.py
linum/composer.py
linum/context.py
linum/exceptions.py
linum/helper.py
linum/layer.py
linum/layer_list.py
linum/task.py
linum/task_part.py
linum/excel_renderer/__init__.py
linum/excel_renderer/excel_renderer.py
linum/excel_renderer/base/__init__.py
linum/excel_renderer/base/cell.py
linum/excel_renderer/base/date_cell.py
linum/excel_renderer/base/date_row.py
linum/excel_renderer/base/row.py
linum/excel_renderer/base/style.py
linum/excel_renderer/calendar/__init__.py
linum/excel_renderer/calendar/calendar.py
linum/excel_renderer/calendar/header/__init__.py
linum/excel_renderer/calendar/header/header.py
linum/excel_renderer/calendar/header/day/__init__.py
linum/excel_renderer/calendar/header/day/day_cell.py
linum/excel_renderer/calendar/header/day/days_row.py
linum/excel_renderer/calendar/header/month/__init__.py
linum/excel_renderer/calendar/header/month/month_cell.py
linum/excel_renderer/calendar/header/month/months_row.py
linum/excel_renderer/calendar/header/weekday/__init__.py
linum/excel_renderer/calendar/header/weekday/weekday_cell.py
linum/excel_renderer/calendar/header/weekday/weekdays_row.py
linum/excel_renderer/calendar/space/__init__.py
linum/excel_renderer/calendar/space/space_cell.py
linum/excel_renderer/calendar/space/space_row.py
linum/excel_renderer/calendar/views/__init__.py
linum/excel_renderer/calendar/views/layer_list_view.py
linum/excel_renderer/calendar/views/layer_view.py
linum/excel_renderer/calendar/views/task_part_view.py
linum/loader/__init__.py
linum/loader/context_schema.yaml
linum/loader/data_schema.yaml
linum/loader/loader.py
linum/styles/__init__.py
linum/styles/color_palettes.py
linum/styles/svg/__init__.py
linum/styles/svg/svg_default_context.yaml
linum/styles/svg/svg_default_style.css
linum/styles/xlsx/__init__.py
linum/styles/xlsx/xlsx_default_context.yaml
linum/svg_renderer/__init__.py
linum/svg_renderer/svg_renderer.py
