Metadata-Version: 2.1
Name: Linum
Version: 0.9.9
Summary: The tool for tasks visualization — like Gantt chart, but compact.
Home-page: https://github.com/chabErch/Linum
Author: chaberch
Author-email: chaberch@yandex.ru
License: MIT
Keywords: Gantt,chart,schedule,Linum,render,visualisation,excel,xlsx
Platform: UNKNOWN
Classifier: Development Status :: 3 - Alpha
Classifier: Environment :: Console
Classifier: License :: OSI Approved :: MIT License
Classifier: Programming Language :: Python
Classifier: Programming Language :: Python :: 3.6
Classifier: Programming Language :: Python :: 3.7
Classifier: Programming Language :: Python :: 3.8
Classifier: Programming Language :: Python :: 3.9
Classifier: Operating System :: OS Independent
License-File: LICENSE
